microcosm_eventsource/__init__.py
microcosm_eventsource/accumulation.py
microcosm_eventsource/controllers.py
microcosm_eventsource/errors.py
microcosm_eventsource/event_types.py
microcosm_eventsource/factory.py
microcosm_eventsource/func.py
microcosm_eventsource/resources.py
microcosm_eventsource/routes.py
microcosm_eventsource/transitioning.py
microcosm_eventsource/ddl/array_sort_unique.create.ddl
microcosm_eventsource/ddl/array_sort_unique.drop.ddl
microcosm_eventsource/ddl/last_agg.create.ddl
microcosm_eventsource/ddl/last_agg.drop.ddl
microcosm_eventsource/ddl/last_agg_sfunc.create.ddl
microcosm_eventsource/ddl/last_agg_sfunc.drop.ddl
microcosm_eventsource/ddl/proc_event_type_delete.create.ddl
microcosm_eventsource/ddl/proc_event_type_delete.drop.ddl
microcosm_eventsource/ddl/proc_event_type_replace.create.ddl
microcosm_eventsource/ddl/proc_event_type_replace.drop.ddl
microcosm_eventsource/ddl/proc_events_create.create.ddl
microcosm_eventsource/ddl/proc_events_create.drop.ddl
microcosm_eventsource/ddl/proc_events_delete.create.ddl
microcosm_eventsource/ddl/proc_events_delete.drop.ddl
microcosm_eventsource/models/__init__.py
microcosm_eventsource/models/alias.py
microcosm_eventsource/models/base.py
microcosm_eventsource/models/meta.py
microcosm_eventsource/models/rollup.py
microcosm_eventsource/stores/__init__.py
microcosm_eventsource/stores/event.py
microcosm_eventsource/stores/rollup.py
microcosm_eventsource-3.0.0.dist-info/LICENSE
microcosm_eventsource-3.0.0.dist-info/METADATA
microcosm_eventsource-3.0.0.dist-info/WHEEL
microcosm_eventsource-3.0.0.dist-info/top_level.txt
microcosm_eventsource-3.0.0.dist-info/RECORD
